README.rst
setup.py
hello_pypi/__init__.py
hello_pypi.egg-info/PKG-INFO
hello_pypi.egg-info/SOURCES.txt
hello_pypi.egg-info/dependency_links.txt
hello_pypi.egg-info/not-zip-safe
hello_pypi.egg-info/top_level.txt