Metadata-Version: 1.0
Name: hello-pypi
Version: 1.1
Summary: An example pypi project
Home-page: https://github.com/smelnicki/hello_pypi
Author: Stephen Melnicki
Author-email: smelnicki@tutamail.com
License: MIT
Platform: UNKNOWN
